Metadata-Version: 2.1
Name: h5cv
Version: 0.1.1
Summary: Command Line utility for cost of aws.
Home-page: https://github.com/toyama0919/h5cv
Author: Hiroshi Toyama
Author-email: toyama0919@gmail.com
License: MIT
Keywords: h5cv hdf5 Python3 cv
Platform: UNKNOWN
Classifier: Programming Language :: Python :: 3.6
Classifier: Programming Language :: Python :: 3.7
Classifier: Programming Language :: Python :: 3.8
Provides-Extra: test
